[
  {
      "pack_id": "unforgiven",
      "id": "DTH021",
      "position": "10622",
      "name": "Epistolary Vezuel",
      "type_id": "warlord",
      "faction_id": "space_marines",
      "loyalty_id": "signature",
      "signature_id": 27,
      "quantity": 1,
      "unique": true,
      "keywords": null,
      "traits": "Dark Angels, Psyker",
      "text": "[REACTION]: After you Deep Strike a card, draw 1 card.",
      "cost": null,
      "attack": 2,
      "health": 6,
      "command_hammers": 0,
      "shields": 0,
      "preparation": false,
      "flavor": "“Repent! For your doom is at hand.”",
      "tts_sheet_position": 6,
      "tts_sheet_url": "http://cloud-3.steamusercontent.com/ugc/1796351328360428715/8DCC8CED2F0CE935D577C3A1EABB25E5B810AF92/",
      "back_traits": "Dark Angels, Psyker",
      "back_text": null,
      "back_attack": 2,
      "back_health": 6,
      "back_tts_sheet_url": "http://cloud-3.steamusercontent.com/ugc/1796351328360429756/25D5BC7545146C4D1B945F6073860BCFCE534962/"
  },
  {
      "pack_id": "unforgiven",
      "id": "DTH022",
      "position": "10624",
      "name": "Vezuel's Hunters",
      "type_id": "army",
      "faction_id": "space_marines",
      "loyalty_id": "signature",
      "quantity": 4,
      "unique": false,
      "keywords": "Deep Strike (1)",
      "traits": "Dark Angels, Soldier",
      "text": "[REACTION]: After you Deep Strike this unit, deal 2 damage to a target enemy army unit at this planet.",
      "cost": 3,
      "attack": 2,
      "health": 2,
      "command_hammers": 1,
      "shields": 0,
      "preparation": false,
      "flavor": null,
      "tts_sheet_position": 1,
      "tts_sheet_url": "http://cloud-3.steamusercontent.com/ugc/1709660756466768947/649FC45A9645099B0843E0A95CB89AD56FA67F64/"
  },
  {
      "pack_id": "unforgiven",
      "id": "DTH023",
      "position": "10625",
      "name": "Dark Angels Cruiser",
      "type_id": "support",
      "faction_id": "space_marines",
      "loyalty_id": "signature",
      "quantity": 1,
      "unique": false,
      "keywords": null,
      "traits": "Dark Angels, Upgrade",
      "text": "[DEPLOY ACTION]: Exhaust this support to put a target unit you control at a planet in reserve.",
      "cost": 0,
      "attack": null,
      "health": null,
      "command_hammers": 0,
      "shields": 0,
      "preparation": false,
      "flavor": "“He's down there, I can feel it.” - Epistolary Vezuel",
      "tts_sheet_position": 0,
      "tts_sheet_url": "http://cloud-3.steamusercontent.com/ugc/1709660756466748646/704CE56F583F868664A49AFAD18EB55267307B5D/"
  },
  {
      "pack_id": "unforgiven",
      "id": "DTH024",
      "position": "10626",
      "name": "Unseen Strike",
      "type_id": "event",
      "faction_id": "space_marines",
      "loyalty_id": "signature",
      "quantity": 2,
      "unique": false,
      "keywords": "Deep Strike (1)",
      "traits": "Tactic",
      "text": "[REACTION]: After you Deep Strike this event, you gain the initiative in this battle.",
      "cost": null,
      "attack": null,
      "health": null,
      "command_hammers": 0,
      "shields": 1,
      "preparation": false,
      "flavor": null,
      "tts_sheet_position": 6,
      "tts_sheet_url": "http://cloud-3.steamusercontent.com/ugc/1709660756466767381/79BC199DE41F230C16B68666982D80FA02F93E6E/"
  },
  {
      "pack_id": "unforgiven",
      "id": "DTH025",
      "position": "10627",
      "name": "Fulgaris",
      "type_id": "attachment",
      "faction_id": "space_marines",
      "loyalty_id": "signature",
      "quantity": 1,
      "unique": true,
      "keywords": null,
      "traits": "Wargear, Weapon",
      "text": "Attach to your warlord.\n[REACTION]: After you Deep Strike a card, attached unit gets +1 ATK and +1 HP until the end of the phase.",
      "cost": 1,
      "attack": null,
      "health": null,
      "command_hammers": 0,
      "shields": 3,
      "preparation": false,
      "flavor": null,
      "tts_sheet_position": 0,
      "tts_sheet_url": "http://cloud-3.steamusercontent.com/ugc/1709660756466753273/62152CAAECAD120FE3B0C564DF9064BFAADE86E0/"
  },
  {
      "pack_id": "unforgiven",
      "id": "DTH026",
      "position": "10628",
      "name": "Firstborn Battalion",
      "type_id": "army",
      "faction_id": "astra_militarum",
      "loyalty_id": "loyal",
      "quantity": 3,
      "unique": false,
      "keywords": null,
      "traits": "Soldier, Vostroya",
      "text": "While you control 3 or more support cards this unit gains Mobile and Ranged.",
      "cost": 4,
      "attack": 3,
      "health": 4,
      "command_hammers": 2,
      "shields": 0,
      "preparation": false,
      "flavor": "The Firstborn carved out swaths of the jungle for their own, building up defenses to hold back the tide of destruction that hungered for their souls.",
      "tts_sheet_position": 0,
      "tts_sheet_url": "http://cloud-3.steamusercontent.com/ugc/1746814290737979382/E41159126D641BB8679ECBACB0DAF5BAA063F449/"
  },
  {
      "pack_id": "unforgiven",
      "id": "DTH027",
      "position": "10629",
      "name": "Clearcut Refuge",
      "type_id": "support",
      "faction_id": "astra_militarum",
      "loyalty_id": "common",
      "quantity": 3,
      "unique": true,
      "keywords": null,
      "traits": "Location",
      "text": "[ACTION]: Exhaust this support to give a target unit +X HP until the end of the phase. X is the highest printed cost among units you control.",
      "cost": 1,
      "attack": null,
      "health": null,
      "command_hammers": 0,
      "shields": 0,
      "preparation": false,
      "flavor": null,
      "tts_sheet_position": 1,
      "tts_sheet_url": "http://cloud-3.steamusercontent.com/ugc/1709660756466744440/B11A9EDAA260017FF5559CC9CA66C4999F11C622/"
  },
  {
      "pack_id": "unforgiven",
      "id": "DTH028",
      "position": "10630",
      "name": "Gorgul Da Slaya",
      "type_id": "army",
      "faction_id": "orks",
      "loyalty_id": "loyal",
      "quantity": 3,
      "unique": true,
      "keywords": null,
      "traits": "Nob, Soldier",
      "text": "[INTERRUPT]: When a unit you control at this planet is declared as an attacker, your opponent cannot trigger effects until after that attack resolves.",
      "cost": 4,
      "attack": 4,
      "health": 5,
      "command_hammers": 0,
      "shields": 0,
      "preparation": false,
      "flavor": "Krump 'em 'ard an fast, give 'em no time ta krump ya back.” -Gorgul Da Slaya",
      "tts_sheet_position": 2,
      "tts_sheet_url": "http://cloud-3.steamusercontent.com/ugc/1709660756466753273/62152CAAECAD120FE3B0C564DF9064BFAADE86E0/"
  },
  {
      "pack_id": "unforgiven",
      "id": "DTH029",
      "position": "10631",
      "name": "Great Iron Gob",
      "type_id": "attachment",
      "faction_id": "orks",
      "loyalty_id": "loyal",
      "quantity": 3,
      "unique": false,
      "keywords": null,
      "traits": "Wargear",
      "text": "Attach to an [ORK] army unit you control.\nAttached unit gains the Nob trait.\nEach army unit you control at this planet gains a command icon.",
      "cost": 2,
      "attack": null,
      "health": null,
      "command_hammers": 0,
      "shields": 2,
      "preparation": false,
      "flavor": null,
      "tts_sheet_position": 4,
      "tts_sheet_url": "http://cloud-3.steamusercontent.com/ugc/1709660756466753273/62152CAAECAD120FE3B0C564DF9064BFAADE86E0/"
  },
  {
      "pack_id": "unforgiven",
      "id": "DTH030",
      "position": "10632",
      "name": "Infectious Nurgling",
      "type_id": "army",
      "faction_id": "chaos",
      "loyalty_id": "common",
      "quantity": 3,
      "unique": false,
      "keywords": "Armorbane",
      "traits": "Daemon, Nurgle",
      "text": null,
      "cost": 1,
      "attack": 2,
      "health": 1,
      "command_hammers": 0,
      "shields": 0,
      "preparation": false,
      "flavor": "Nurglings are blobs of disease and contagion that have sprung to life within the innards of a Great Unclean One. When they have grown strong enough, they leave the Greater Daemon's body by tearing their way out with sickening claws.",
      "tts_sheet_position": 0,
      "tts_sheet_url": "http://cloud-3.steamusercontent.com/ugc/1709660756466757126/19D76838525DAFC22EF1DAE261FFAB18271FEF9E/"
  },
  {
      "pack_id": "unforgiven",
      "id": "DTH031",
      "position": "10633",
      "name": "Seekers of Slaanesh",
      "type_id": "army",
      "faction_id": "chaos",
      "loyalty_id": "common",
      "quantity": 3,
      "unique": false,
      "keywords": "No Wargear Attachments",
      "traits": "Daemon, Elite, Slaanesh",
      "text": "[ACTION]: Sacrifice a Cultist unit at this planet to draw 1 card.",
      "cost": 5,
      "attack": 4,
      "health": 5,
      "command_hammers": 2,
      "shields": 0,
      "preparation": false,
      "flavor": null,
      "tts_sheet_position": 4,
      "tts_sheet_url": "http://cloud-3.steamusercontent.com/ugc/1709660756466764516/E43860A501B3E03A41F67F9A114D06785EB57E7B/"
  },
  {
      "pack_id": "unforgiven",
      "id": "DTH032",
      "position": "10634",
      "name": "Mark of Slaanesh",
      "type_id": "attachment",
      "faction_id": "chaos",
      "loyalty_id": "common",
      "quantity": 3,
      "unique": false,
      "keywords": null,
      "traits": "Curse, Slaanesh",
      "text": "Attach to an army unit you control.\n[INTERRUPT]: When attached unit leaves play, move an army unit you control to this planet.",
      "cost": 0,
      "attack": null,
      "health": null,
      "command_hammers": 0,
      "shields": 1,
      "preparation": false,
      "flavor": null,
      "tts_sheet_position": 6,
      "tts_sheet_url": "http://cloud-3.steamusercontent.com/ugc/1709660756466758712/DA1FCC8EB8FE57EAD3FDD4E50403E7E7A46472CC/"
  },
  {
      "pack_id": "unforgiven",
      "id": "DTH033",
      "position": "10635",
      "name": "Mandrake Cutthroat",
      "type_id": "army",
      "faction_id": "dark_eldar",
      "loyalty_id": "common",
      "quantity": 3,
      "unique": false,
      "keywords": "Deep Strike (1)",
      "traits": "Warrior",
      "text": "[REACTION]: After you Deep Strike this unit, destroy a target Ally unit at this planet.",
      "cost": 3,
      "attack": 2,
      "health": 2,
      "command_hammers": 1,
      "shields": 0,
      "preparation": false,
      "flavor": null,
      "tts_sheet_position": 5,
      "tts_sheet_url": "http://cloud-3.steamusercontent.com/ugc/1709660756466758712/DA1FCC8EB8FE57EAD3FDD4E50403E7E7A46472CC/"
  },
  {
      "pack_id": "unforgiven",
      "id": "DTH034",
      "position": "10636",
      "name": "A Thousand Cuts",
      "type_id": "event",
      "faction_id": "dark_eldar",
      "loyalty_id": "loyal",
      "quantity": 3,
      "unique": false,
      "keywords": null,
      "traits": "Tactic, Torture",
      "text": "[COMBAT ACTION]: Deal 1 damage to a target non-Elite army unit. Then, shuffle this card back into your deck.",
      "cost": 1,
      "attack": null,
      "health": null,
      "command_hammers": 0,
      "shields": 2,
      "preparation": false,
      "flavor": "One...Two...Three...Four",
      "tts_sheet_position": 2,
      "tts_sheet_url": "http://cloud-3.steamusercontent.com/ugc/1709660756466770224/59A4EC4E4B98F0BC5C295F6E56611B092E20AA64/"
  },
  {
      "pack_id": "unforgiven",
      "id": "DTH035",
      "position": "10637",
      "name": "Adherent Outcast",
      "type_id": "army",
      "faction_id": "eldar",
      "loyalty_id": "common",
      "quantity": 3,
      "unique": false,
      "keywords": null,
      "traits": "Scout",
      "text": "Each Elite unit you control at this planet gains Flying.",
      "cost": 2,
      "attack": 1,
      "health": 3,
      "command_hammers": 0,
      "shields": 0,
      "preparation": false,
      "flavor": "Eldar that walk the path of the Outcast will still fight for their race in times of war, especially against the machinations of Slaanesh.",
      "tts_sheet_position": 4,
      "tts_sheet_url": "http://cloud-3.steamusercontent.com/ugc/1709660756466770224/59A4EC4E4B98F0BC5C295F6E56611B092E20AA64/"
  },
  {
      "pack_id": "unforgiven",
      "id": "DTH036",
      "position": "10638",
      "name": "Concealing Darkness",
      "type_id": "event",
      "faction_id": "eldar",
      "loyalty_id": "common",
      "quantity": 3,
      "unique": false,
      "keywords": "Deep Strike (1)",
      "traits": "Power",
      "text": "[REACTION]: After you Deep Strike this event, you may deploy each [ELDAR] unit in your hand at this planet as though it had Ambush until the end of the phase.",
      "cost": null,
      "attack": null,
      "health": null,
      "command_hammers": 0,
      "shields": 1,
      "preparation": false,
      "flavor": null,
      "tts_sheet_position": 4,
      "tts_sheet_url": "http://cloud-3.steamusercontent.com/ugc/1709660756466744440/B11A9EDAA260017FF5559CC9CA66C4999F11C622/"
  },
  {
      "pack_id": "unforgiven",
      "id": "DTH037",
      "position": "10639",
      "name": "Grav Inhibitor Drone",
      "type_id": "army",
      "faction_id": "tau",
      "loyalty_id": "common",
      "quantity": 3,
      "unique": false,
      "keywords": null,
      "traits": "Drone",
      "text": "Each unit with printed cost 2 or lower at this planet cannot attack while a unit with printed cost 3 or higher at this planet is ready.",
      "cost": 1,
      "attack": 0,
      "health": 4,
      "command_hammers": 0,
      "shields": 0,
      "preparation": false,
      "flavor": null,
      "tts_sheet_position": 3,
      "tts_sheet_url": "http://cloud-3.steamusercontent.com/ugc/1709660756466753273/62152CAAECAD120FE3B0C564DF9064BFAADE86E0/"
  },
  {
      "pack_id": "unforgiven",
      "id": "DTH038",
      "position": "10640",
      "name": "Missile Pod",
      "type_id": "attachment",
      "faction_id": "tau",
      "loyalty_id": "common",
      "quantity": 3,
      "unique": false,
      "keywords": null,
      "traits": "Hardpoint",
      "text": "Attach to a Pilot or Vehicle unit you control.\n[DEPLOY ACTION]: Sacrifice this attachment to deal 3 damage to a target enemy army unit in your opponent's HQ or destroy a target support card.",
      "cost": 2,
      "attack": null,
      "health": null,
      "command_hammers": 0,
      "shields": 1,
      "preparation": false,
      "flavor": null,
      "tts_sheet_position": 3,
      "tts_sheet_url": "http://cloud-3.steamusercontent.com/ugc/1746814707116647635/F40F9650671CF5B21E7C386FDD47E3789613A8FC/"
  },
  {
      "pack_id": "unforgiven",
      "id": "DTH039",
      "position": "10641",
      "name": "Caustic Tyrannofex",
      "type_id": "army",
      "faction_id": "tyranids",
      "loyalty_id": "common",
      "quantity": 3,
      "unique": false,
      "keywords": null,
      "traits": "Creature, Elite, Leviathan",
      "text": "[REACTION]: After you win a command struggle at this planet, until the end of the round, this unit gains “Hive Mind - Each Termagant token you control at this planet gains Armorbane.”",
      "cost": 5,
      "attack": 4,
      "health": 4,
      "command_hammers": 3,
      "shields": 0,
      "preparation": false,
      "flavor": null,
      "tts_sheet_position": 0,
      "tts_sheet_url": "http://cloud-3.steamusercontent.com/ugc/1709660756466744440/B11A9EDAA260017FF5559CC9CA66C4999F11C622/"
  },
  {
      "pack_id": "unforgiven",
      "id": "DTH040",
      "position": "10642",
      "name": "Loamy Broodhive",
      "type_id": "support",
      "faction_id": "tyranids",
      "loyalty_id": "common",
      "quantity": 3,
      "unique": false,
      "keywords": null,
      "traits": "Location",
      "text": "[REACTION]: After you deploy an Elite unit, exhaust this support to put 2 Termagant tokens into play at the same planet as that unit.",
      "cost": 1,
      "attack": null,
      "health": null,
      "command_hammers": 0,
      "shields": 0,
      "preparation": false,
      "flavor": null,
      "tts_sheet_position": 3,
      "tts_sheet_url": "http://cloud-3.steamusercontent.com/ugc/1709660756466758712/DA1FCC8EB8FE57EAD3FDD4E50403E7E7A46472CC/"
  },
  {
      "pack_id": "unforgiven",
      "id": "DTH041",
      "position": "10643",
      "name": "Hunting Acanthrites",
      "type_id": "army",
      "faction_id": "necrons",
      "loyalty_id": "common",
      "quantity": 3,
      "unique": false,
      "keywords": null,
      "traits": "Drone",
      "text": "Each unit with printed cost 2 or lower at this planet gets -1 HP",
      "cost": 3,
      "attack": 1,
      "health": 3,
      "command_hammers": 0,
      "shields": 0,
      "preparation": false,
      "flavor": "Ancanthrites are murderous constructs used to weaken an enemy force before the rest of the Necrons sweep in for the slaughter.",
      "tts_sheet_position": 2,
      "tts_sheet_url": "http://cloud-3.steamusercontent.com/ugc/1709660756466755908/D158468C6151C189908620DA958D27813C25F8E9/"
  },
  {
      "pack_id": "unforgiven",
      "id": "DTH042",
      "position": "10644",
      "name": "Defensive Protocols",
      "type_id": "event",
      "faction_id": "necrons",
      "loyalty_id": "common",
      "quantity": 3,
      "unique": false,
      "keywords": "Deep Strike (2)",
      "traits": "Tactic",
      "text": "[REACTION]: After you Deep Strike this event, until the end of this battle's first combat round, reduce all damage taken by [NECRON] units you control to 1.",
      "cost": null,
      "attack": null,
      "health": null,
      "command_hammers": 0,
      "shields": 1,
      "preparation": false,
      "flavor": null,
      "tts_sheet_position": 5,
      "tts_sheet_url": "http://cloud-3.steamusercontent.com/ugc/1709660756466748646/704CE56F583F868664A49AFAD18EB55267307B5D/"
  }
]